request_cli/__init__.py
request_cli/_base_httpclient.py
request_cli/_httpclient.py
request_cli/_httpclient_utils.py
request_cli-1.0.0.dist-info/LICENSE
request_cli-1.0.0.dist-info/METADATA
request_cli-1.0.0.dist-info/WHEEL
request_cli-1.0.0.dist-info/top_level.txt
request_cli-1.0.0.dist-info/RECORD
