Metadata-Version: 2.1
Name: request-cli
Version: 1.0.0
Summary: requests
Home-page: 
Author: PengKe
Author-email: 925330867@qq.com
Classifier: Programming Language :: Python :: 3
Classifier: License :: OSI Approved :: MIT License
Classifier: Operating System :: OS Independent
Requires-Python: >=3.6
License-File: LICENSE
Requires-Dist: yarl
Requires-Dist: requests
